{"id": 26063, "title": "Forest", "description": "A dense forest. The soil beneath the debris layer is rich and dark, with white fungal strands visible through out. The sky is almostly completely obscured by branches and leaves. Leaves, sticks, and other debris litters the ground. The land is gently sloped up to the north, gently sloped up to the east, gently sloped down to the south, gently sloped down to the west.", "exits": {"north": {"is_door": false, "is_open": true, "direction": "north", "room_to": 25863}, "west": {"is_door": false, "is_open": true, "direction": "west", "room_to": 26062}, "east": {"is_door": false, "is_open": true, "direction": "east", "room_to": 26064}, "south": {"is_door": false, "is_open": true, "direction": "south", "room_to": 26263}}, "items": ["young european oak tree", "ancient european oak tree"]}