{"id": 72, "title": "Forest", "description": "A dense forest. Leaves, sticks, and other debris litters the ground. The soil beneath the debris layer is rich and dark, with white fungal strands visible through out. The land is flat to the north, gently sloped up to the east, gently sloped up to the south, gently sloped up to the west.", "exits": {"west": {"is_door": false, "is_open": true, "direction": "west", "room_to": 71}, "east": {"is_door": false, "is_open": true, "direction": "east", "room_to": 73}, "south": {"is_door": false, "is_open": true, "direction": "south", "room_to": 272}}, "items": ["european oak sapling", "mature european oak tree", "mature european oak tree"]}