{"id": 5941, "title": "Forest", "description": "A dense forest.", "exits": {"west": {"is_door": false, "is_open": true, "direction": "west", "room_to": 5841}, "north": {"is_door": false, "is_open": true, "direction": "north", "room_to": 5940}, "east": {"is_door": false, "is_open": true, "direction": "east", "room_to": 6041}, "south": {"is_door": false, "is_open": true, "direction": "south", "room_to": 5942}}, "items": ["european oak sapling", "european oak sapling", "young european oak tree", "mature european oak tree", "mature european oak tree", "european oak sapling", "european oak tree", "mature european oak tree", "ancient european oak tree"]}